pti_andante/__init__.py
pti_andante/cli.py
pti_andante/dplib.py
PTIAndante-1.0.2.dist-info/METADATA
PTIAndante-1.0.2.dist-info/WHEEL
PTIAndante-1.0.2.dist-info/entry_points.txt
PTIAndante-1.0.2.dist-info/top_level.txt
PTIAndante-1.0.2.dist-info/RECORD
