Metadata-Version: 2.1
Name: PTIAndante
Version: 1.0.2
Summary: PTI Demand Planner Utilities
Home-page: https://gitlab.com/paragon-is/erp/pti_andante.git
Author: Agustianes Umbara Suwardi
Author-email: agustianes.us@pti-cosmetics.com
License: UNKNOWN
Platform: UNKNOWN
Classifier: Programming Language :: Python :: 3
Classifier: License :: OSI Approved :: GNU General Public License v3 (GPLv3)
Classifier: Operating System :: OS Independent
Requires-Python: >=3.6
Requires-Dist: Click (==7.0)
Requires-Dist: loguru (==0.3.2)
Requires-Dist: python-dateutil
Requires-Dist: xlrd (==1.2.0)
